one/__init__.py
one/hello.py
one/main.py
Test19991021-3.6.0.dist-info/METADATA
Test19991021-3.6.0.dist-info/WHEEL
Test19991021-3.6.0.dist-info/top_level.txt
Test19991021-3.6.0.dist-info/RECORD
