Metadata-Version: 2.1
Name: Test19991021
Version: 3.6.0
Summary: my package
